{
	"symbol": "APM",
	"name": "Andean Precious Metals Corp.",
	"price": 3.25,
	"priceChange": 0.01,
	"percentChange": 0.308642,
	"exchangeName": "Toronto Stock Exchange",
	"exShortName": "TSX",
	"exchangeCode": "TSX",
	"marketPlace": null,
	"sector": "Materials",
	"industry": "Mining",
	"volume": 282267,
	"openPrice": 3.29,
	"dayHigh": 3.29,
	"dayLow": 3.22,
	"MarketCap": 481708725,
	"MarketCapAllClasses": 480330182,
	"peRatio": 10.81,
	"prevClose": 3.24,
	"dividendFrequency": null,
	"dividendYield": null,
	"dividendAmount": null,
	"dividendCurrency": null,
	"beta": 1.094091,
	"eps": 0.32,
	"exDividendDate": "",
	"longDescription": "Andean is a growing precious metals producer focused on top tier jurisdictions in the Americas. The Company owns and operates the San Bartolome processing facility in Potosi, Bolivia and the Soledad Mountain mine in Kern County, California, and is well funded to act on future growth opportunities. Andeans leadership team is committed to creating value; fostering safe, sustainable and responsible operations, and achieving our ambition to be a mid tier precious metals producer.",
	"fulldescription": "Andean is a growing precious metals producer focused on top tier jurisdictions in the Americas. The Company owns and operates the San Bartolome processing facility in Potosi, Bolivia and the Soledad Mountain mine in Kern County, California, and is well funded to act on future growth opportunities. Andeans leadership team is committed to creating value; fostering safe, sustainable and responsible operations, and achieving our ambition to be a mid tier precious metals producer.",
	"website": "https://www.andeanpm.com",
	"email": "",
	"phoneNumber": "+1 647 480-1550",
	"fullAddress": "1055 West Georgia Street,P.O. Box 11117, Vancouver, BC, CA",
	"employees": "0",
	"shareOutStanding": 148218069,
	"totalDebtToEquity": 0.45,
	"totalSharesOutStanding": 147793902,
	"sharesESCROW": 0,
	"vwap": 3.25890369,
	"dividendPayDate": null,
	"weeks52high": 3.31,
	"weeks52low": 0.91,
	"alpha": 0.021367,
	"averageVolume10D": 271600,
	"averageVolume20D": 215178,
	"averageVolume30D": 209278,
	"averageVolume50D": 207790,
	"priceToBook": 2.13,
	"priceToCashFlow": 12.5,
	"returnOnEquity": 23.09,
	"returnOnAssets": 11.33,
	"day21MovingAvg": 2.828095,
	"day50MovingAvg": 2.3388,
	"day200MovingAvg": 1.71985,
	"dividend3Years": "",
	"dividend5Years": "",
	"datatype": "equity",
	"issueType": "CS",
	"close": 3.25,
	"qmdescription": "Silver",
	"__typename": "Company"
}