{
	"symbol": "ARTI",
	"name": "Evolve Artificial Intelligence Fund",
	"price": 12.69,
	"priceChange": -0.05,
	"percentChange": -0.392465,
	"exchangeName": "Toronto Stock Exchange",
	"exShortName": "TSX",
	"exchangeCode": "TSX",
	"marketPlace": null,
	"sector": "",
	"industry": "",
	"volume": 20700,
	"openPrice": 12.8,
	"dayHigh": 12.8,
	"dayLow": 12.64,
	"MarketCap": 12055500,
	"MarketCapAllClasses": 0,
	"peRatio": 34.6,
	"prevClose": 12.74,
	"dividendFrequency": null,
	"dividendYield": null,
	"dividendAmount": null,
	"dividendCurrency": null,
	"beta": 0.858591,
	"eps": null,
	"exDividendDate": "",
	"longDescription": "ARTI collaborates with Boosted.ai to utilize their state-of-the-art generative AI platform and proprietary scoring to strategically select companies set to benefit significantly from AI integration in the years ahead.",
	"fulldescription": "ARTI collaborates with Boosted.ai to utilize their state-of-the-art generative AI platform and proprietary scoring to strategically select companies set to benefit significantly from AI integration in the years ahead. The investment objective of the Evolve Fund is to provide exposure to securities of publicly traded issuers that the Manager has determined are expected to benefit from increased adoption of AI.",
	"website": "",
	"email": "",
	"phoneNumber": "",
	"fullAddress": "CA",
	"employees": "",
	"shareOutStanding": 950000,
	"totalDebtToEquity": "",
	"totalSharesOutStanding": 0,
	"sharesESCROW": null,
	"vwap": 12.6852173,
	"dividendPayDate": null,
	"weeks52high": 12.8,
	"weeks52low": 8,
	"alpha": 0.007188,
	"averageVolume10D": 4326,
	"averageVolume20D": 2576,
	"averageVolume30D": 2130,
	"averageVolume50D": 1847,
	"priceToBook": 8.68,
	"priceToCashFlow": "",
	"returnOnEquity": "",
	"returnOnAssets": "",
	"day21MovingAvg": 12.283333,
	"day50MovingAvg": 11.6412,
	"day200MovingAvg": 11.35105,
	"dividend3Years": "",
	"dividend5Years": "",
	"datatype": "etf",
	"issueType": "ET",
	"close": 12.66,
	"qmdescription": "",
	"__typename": "Company"
}