{
	"symbol": "CACB",
	"name": "CIBC Active Investment Grade Corporate Bond ETF",
	"price": 19.93,
	"priceChange": 0.04,
	"percentChange": 0.201106,
	"exchangeName": "Toronto Stock Exchange",
	"exShortName": "TSX",
	"exchangeCode": "TSX",
	"marketPlace": null,
	"sector": "",
	"industry": "",
	"volume": 1205,
	"openPrice": 19.81,
	"dayHigh": 19.93,
	"dayLow": 19.81,
	"MarketCap": 1542582000,
	"MarketCapAllClasses": 0,
	"peRatio": "",
	"prevClose": 19.89,
	"dividendFrequency": "Monthly",
	"dividendYield": 4.248,
	"dividendAmount": 0.077,
	"dividendCurrency": "CAD",
	"beta": 0.263726,
	"eps": null,
	"exDividendDate": "2024-11-29 00:00:00.0",
	"longDescription": "CIBC Active Investment Grade Corporate Bond ETF (referred to as the CIBC ETF) seeks to generate a high level of current income while preserving capital by investing primarily in bonds, debentures, notes and other debt instruments of Canadian issuers. The CIBC ETF invests primarily in Canadian investment grade corporate bonds based primarily on security selection, sector allocation, and average term-to-maturity. Portoflio assets are allocated to those securities and sectors of the corporate bond market that the portfolio advisor expects will outperform. The CIBC ETF undertakes a bottom-up analysis of corporate bond issuers combined with top-down analysis of a sectors potential in a given economic environment.",
	"fulldescription": "CIBC Active Investment Grade Corporate Bond ETF (referred to as the CIBC ETF) seeks to generate a high level of current income while preserving capital by investing primarily in bonds, debentures, notes and other debt instruments of Canadian issuers. The CIBC ETF invests primarily in Canadian investment grade corporate bonds based primarily on security selection, sector allocation, and average term-to-maturity. Portoflio assets are allocated to those securities and sectors of the corporate bond market that the portfolio advisor expects will outperform. The CIBC ETF undertakes a bottom-up analysis of corporate bond issuers combined with top-down analysis of a sectors potential in a given economic environment.",
	"website": "www.renaissanceinvestments.ca",
	"email": "info@renaissanceinvestments.ca",
	"phoneNumber": "888 888 FUND",
	"fullAddress": "1500, Robert-Bourassa Blvd, Suite 800, Montreal, QC, CA",
	"employees": "",
	"shareOutStanding": 77400000,
	"totalDebtToEquity": "",
	"totalSharesOutStanding": 0,
	"sharesESCROW": null,
	"vwap": 19.8716666,
	"dividendPayDate": "2024-12-04",
	"weeks52high": 20.23,
	"weeks52low": 17.907846,
	"alpha": 0.00239,
	"averageVolume10D": 64111,
	"averageVolume20D": 101269,
	"averageVolume30D": 110735,
	"averageVolume50D": 99499,
	"priceToBook": null,
	"priceToCashFlow": "",
	"returnOnEquity": "",
	"returnOnAssets": "",
	"day21MovingAvg": 19.968864,
	"day50MovingAvg": 19.95185,
	"day200MovingAvg": 19.24503,
	"dividend3Years": "",
	"dividend5Years": "",
	"datatype": "etf",
	"issueType": "ET",
	"close": 19.89,
	"qmdescription": "",
	"__typename": "Company"
}