{
	"symbol": "CMAG",
	"name": "CI Munro Alternative Global Growth Fund",
	"price": 37.25,
	"priceChange": 0.02,
	"percentChange": 0.05372,
	"exchangeName": "Toronto Stock Exchange",
	"exShortName": "TSX",
	"exchangeCode": "TSX",
	"marketPlace": null,
	"sector": "",
	"industry": "",
	"volume": 10001,
	"openPrice": 37.04,
	"dayHigh": 37.25,
	"dayLow": 37.04,
	"MarketCap": 344562500,
	"MarketCapAllClasses": 0,
	"peRatio": 37.2,
	"prevClose": 37.23,
	"dividendFrequency": null,
	"dividendYield": null,
	"dividendAmount": null,
	"dividendCurrency": null,
	"beta": 0.330097,
	"eps": null,
	"exDividendDate": "",
	"longDescription": "The CI Munro Alternative Global Growth ETF (the Fund) seeks to generate risk-adjusted, absolute returns through exposure to global growth equities over the medium to long term, while maintaining a capital preservation mindset. The Fund will invest primarily in listed international equities, deploying a longshort equities strategy with a long bias. The investment strategy is designed to identify sustainable growth trends that are underappreciated and mispriced by the market, and the resulting winning and losing stocks.",
	"fulldescription": "The CI Munro Alternative Global Growth ETF (the Fund) seeks to generate risk-adjusted, absolute returns through exposure to global growth equities over the medium to long term, while maintaining a capital preservation mindset. The Fund will invest primarily in listed international equities, deploying a longshort equities strategy with a long bias. The investment strategy is designed to identify sustainable growth trends that are underappreciated and mispriced by the market, and the resulting winning and losing stocks.",
	"website": "www.ci.com",
	"email": "service@cifunds.com",
	"phoneNumber": "+1 416 3641145",
	"fullAddress": "15 York Street, 2nd Floor, Toronto, ON, CA",
	"employees": "",
	"shareOutStanding": 9250000,
	"totalDebtToEquity": "",
	"totalSharesOutStanding": 0,
	"sharesESCROW": null,
	"vwap": 37.1569,
	"dividendPayDate": null,
	"weeks52high": 37.35,
	"weeks52low": 26.38,
	"alpha": 0.008539,
	"averageVolume10D": 4344,
	"averageVolume20D": 3215,
	"averageVolume30D": 4263,
	"averageVolume50D": 2819,
	"priceToBook": 7.31,
	"priceToCashFlow": 15.4,
	"returnOnEquity": 21.14,
	"returnOnAssets": 7.88,
	"day21MovingAvg": 36.40619,
	"day50MovingAvg": 35.6314,
	"day200MovingAvg": 33.69325,
	"dividend3Years": "",
	"dividend5Years": "",
	"datatype": "etf",
	"issueType": "ET",
	"close": 37.25,
	"qmdescription": "",
	"__typename": "Company"
}