{
	"symbol": "DMEE",
	"name": "Desjardins Emerging Markets Equity Index ETF",
	"price": 20.83,
	"priceChange": -0.15,
	"percentChange": -0.714967,
	"exchangeName": "Toronto Stock Exchange",
	"exShortName": "TSX",
	"exchangeCode": "TSX",
	"marketPlace": null,
	"sector": "",
	"industry": "",
	"volume": 570,
	"openPrice": 20.71,
	"dayHigh": 20.83,
	"dayLow": 20.71,
	"MarketCap": 308284000,
	"MarketCapAllClasses": 0,
	"peRatio": 4.38,
	"prevClose": 20.98,
	"dividendFrequency": "Quarterly",
	"dividendYield": 2.605,
	"dividendAmount": 0.3,
	"dividendCurrency": "CAD",
	"beta": 0.790937,
	"eps": null,
	"exDividendDate": "2025-06-23 00:00:00.0",
	"longDescription": "The investment strategy of the ETF is to invest, directly or indirectly, in a portfolio of emerging markets that closely matches the Index. The index is composed of large and mid-cap securities of Emerging Markets companies. The ETF seeks to replicate, to the extent reasonably possible and before fees and expenses, the performance of an Emerging Market Equity Index. Currently, DMEE seeks to replicate the performance of the Solactive GBS Emerging Markets Large  Mid Cap CAD Index (CA NTR) (the index).",
	"fulldescription": "The investment strategy of the ETF is to invest, directly or indirectly, in a portfolio of emerging markets that closely matches the Index. The index is composed of large and mid-cap securities of Emerging Markets companies. The ETF seeks to replicate, to the extent reasonably possible and before fees and expenses, the performance of an Emerging Market Equity Index. Currently, DMEE seeks to replicate the performance of the Solactive GBS Emerging Markets Large  Mid Cap CAD Index (CA NTR) (the index).",
	"website": "",
	"email": "",
	"phoneNumber": "",
	"fullAddress": "CA",
	"employees": "",
	"shareOutStanding": 14800000,
	"totalDebtToEquity": "",
	"totalSharesOutStanding": 0,
	"sharesESCROW": null,
	"vwap": 20.742,
	"dividendPayDate": "2025-06-30",
	"weeks52high": 21.05,
	"weeks52low": 17.58,
	"alpha": 0.007444,
	"averageVolume10D": 5363,
	"averageVolume20D": 5310,
	"averageVolume30D": 7200,
	"averageVolume50D": 6578,
	"priceToBook": 0.72,
	"priceToCashFlow": "",
	"returnOnEquity": "",
	"returnOnAssets": "",
	"day21MovingAvg": 20.365948,
	"day50MovingAvg": 19.870861,
	"day200MovingAvg": 19.517282,
	"dividend3Years": "",
	"dividend5Years": "",
	"datatype": "etf",
	"issueType": "",
	"close": 20.83,
	"qmdescription": "",
	"__typename": "Company"
}