{
	"symbol": "ETSX",
	"name": "Evolve S&P/TSX 60 Enhanced Yield Fund",
	"price": 21.66,
	"priceChange": 0.06,
	"percentChange": 0.277778,
	"exchangeName": "Toronto Stock Exchange",
	"exShortName": "TSX",
	"exchangeCode": "TSX",
	"marketPlace": null,
	"sector": "",
	"industry": "",
	"volume": 860,
	"openPrice": 21.66,
	"dayHigh": 21.66,
	"dayLow": 21.66,
	"MarketCap": 34656000,
	"MarketCapAllClasses": 0,
	"peRatio": 13.72,
	"prevClose": 21.6,
	"dividendFrequency": "Monthly",
	"dividendYield": 8.868,
	"dividendAmount": 0.16,
	"dividendCurrency": "CAD",
	"beta": 0.961993,
	"eps": null,
	"exDividendDate": "2024-11-29 00:00:00.0",
	"longDescription": "ETSX seeks to provide long-term capital growth by replicating, net of fees and expenses, the performance of the S&P/TSX 60 Index, or any successor thereto, while mitigating downside risk. ETSX invests primarily in the equity constituents of the S&P/TSX 60 Index, or any successor thereto, while writing covered call options on up to 33% of the portfolio, at the discretion of the Manager. The level of covered call option writing may vary based on market volatility and other factors.",
	"fulldescription": "ETSX seeks to provide long-term capital growth by replicating, net of fees and expenses, the performance of the S&P/TSX 60 Index, or any successor thereto, while mitigating downside risk. ETSX invests primarily in the equity constituents of the S&P/TSX 60 Index, or any successor thereto, while writing covered call options on up to 33% of the portfolio, at the discretion of the Manager. The level of covered call option writing may vary based on market volatility and other factors.",
	"website": "www.evolveetfs.com",
	"email": "",
	"phoneNumber": "",
	"fullAddress": "161 Bay Street, Suite 2700, Toronto ON M5J 2S1, Toronto, ON, CA",
	"employees": "",
	"shareOutStanding": 1600000,
	"totalDebtToEquity": "",
	"totalSharesOutStanding": 0,
	"sharesESCROW": null,
	"vwap": 21.66,
	"dividendPayDate": "2024-12-06",
	"weeks52high": 21.66,
	"weeks52low": 17.301946,
	"alpha": 0.001064,
	"averageVolume10D": 2338,
	"averageVolume20D": 4517,
	"averageVolume30D": 3330,
	"averageVolume50D": 3388,
	"priceToBook": 1.37,
	"priceToCashFlow": "",
	"returnOnEquity": "",
	"returnOnAssets": "",
	"day21MovingAvg": 21.10141,
	"day50MovingAvg": 20.81644,
	"day200MovingAvg": 19.398869,
	"dividend3Years": "",
	"dividend5Years": "",
	"datatype": "etf",
	"issueType": "",
	"close": 21.65,
	"qmdescription": "",
	"__typename": "Company"
}