{
	"symbol": "EXRO.WT.A",
	"name": "Exro Technologies Inc. common share purchase warrants",
	"price": 0.02,
	"priceChange": 0,
	"percentChange": 0,
	"exchangeName": "Toronto Stock Exchange",
	"exShortName": "TSX",
	"exchangeCode": "TSX",
	"marketPlace": null,
	"sector": "",
	"industry": "",
	"volume": 0,
	"openPrice": null,
	"dayHigh": null,
	"dayLow": null,
	"MarketCap": 749995,
	"MarketCapAllClasses": 10992560,
	"peRatio": "",
	"prevClose": 0.02,
	"dividendFrequency": null,
	"dividendYield": null,
	"dividendAmount": null,
	"dividendCurrency": null,
	"beta": 0.950361,
	"eps": null,
	"exDividendDate": "",
	"longDescription": "Exro Technologies Inc is a Canadian based company commercializing patented technology designed to advance existing rotating electric machines. It is engaged in the production of electronics for electric motors and generators. The company serves car/truck, bus, generator, appliance, elevator, escalator, conveyor, ship drive, fan, pump, crane, HVAC, compressor, vacuum, train, industrial motor, wind turbine, and subway markets.",
	"fulldescription": "Exro Technologies Inc is a Canadian based company commercializing patented technology designed to advance existing rotating electric machines. It is engaged in the production of electronics for electric motors and generators. The company serves car/truck, bus, generator, appliance, elevator, escalator, conveyor, ship drive, fan, pump, crane, HVAC, compressor, vacuum, train, industrial motor, wind turbine, and subway markets.",
	"website": "https://www.exro.com",
	"email": "",
	"phoneNumber": "(604) 674-7746",
	"fullAddress": "1177 West Hastings Street,Suite 2300, Vancouver, BC, CA",
	"employees": "155",
	"shareOutStanding": 37499725,
	"totalDebtToEquity": "",
	"totalSharesOutStanding": 549627961,
	"sharesESCROW": null,
	"vwap": null,
	"dividendPayDate": null,
	"weeks52high": 0.15,
	"weeks52low": 0.005,
	"alpha": -0.175914,
	"averageVolume10D": 22630,
	"averageVolume20D": 37940,
	"averageVolume30D": 56927,
	"averageVolume50D": 54337,
	"priceToBook": -641.65,
	"priceToCashFlow": -0.8,
	"returnOnEquity": -3066.7,
	"returnOnAssets": -244.79,
	"day21MovingAvg": 0.016905,
	"day50MovingAvg": 0.0186,
	"day200MovingAvg": 0.03595,
	"dividend3Years": "",
	"dividend5Years": "",
	"datatype": "equity",
	"issueType": "WT",
	"close": 0.02,
	"qmdescription": "",
	"__typename": "Company"
}