{
	"symbol": "FN",
	"name": "First National Financial Corporation",
	"price": 44.53,
	"priceChange": 0.02,
	"percentChange": 0.044934,
	"exchangeName": "Toronto Stock Exchange",
	"exShortName": "TSX",
	"exchangeCode": "TSX",
	"marketPlace": null,
	"sector": "Finance",
	"industry": "Banking",
	"volume": 32596,
	"openPrice": 44.85,
	"dayHigh": 44.85,
	"dayLow": 44.39,
	"MarketCap": 2670349614,
	"MarketCapAllClasses": 2670349614,
	"peRatio": 14.75,
	"prevClose": 44.51,
	"dividendFrequency": null,
	"dividendYield": 5.614,
	"dividendAmount": 0.708334,
	"dividendCurrency": "CAD",
	"beta": 1.085747,
	"eps": 3.01,
	"exDividendDate": "2024-11-29 00:00:00.0",
	"longDescription": "First National Financial Corp is the parent company of First National Financial LP, a Canadian originator, underwriter, and servicer of predominantly prime residential and commercial mortgages. The company controls its First National Mortgage Investment Fund, which manages economic exposure to a diversified portfolio of primarily commercial mezzanine mortgages. Most mortgages originated by First National are funded either by placement with institutional investors or through securitization conduits, in each case with retained servicing. In general, originations are allocated from one funding source to another depending on market conditions and strategic considerations related to maintaining diversified funding sources.",
	"fulldescription": "First National Financial Corp is the parent company of First National Financial LP, a Canadian originator, underwriter, and servicer of predominantly prime residential and commercial mortgages. The company controls its First National Mortgage Investment Fund, which manages economic exposure to a diversified portfolio of primarily commercial mezzanine mortgages. Most mortgages originated by First National are funded either by placement with institutional investors or through securitization conduits, in each case with retained servicing. In general, originations are allocated from one funding source to another depending on market conditions and strategic considerations related to maintaining diversified funding sources.",
	"website": "https://www.firstnational.ca",
	"email": "rob.inglis@firstnational.ca",
	"phoneNumber": "+1 416 593-1100",
	"fullAddress": "16 York Street,Suite 1900, Toronto, ON, CA",
	"employees": "1686",
	"shareOutStanding": 59967429,
	"totalDebtToEquity": 71.11,
	"totalSharesOutStanding": 59967429,
	"sharesESCROW": null,
	"vwap": 44.5778481,
	"dividendPayDate": "2024-12-13",
	"weeks52high": 44.85,
	"weeks52low": 35.15,
	"alpha": 0.000302,
	"averageVolume10D": 33280,
	"averageVolume20D": 36213,
	"averageVolume30D": 31389,
	"averageVolume50D": 30266,
	"priceToBook": 4.15,
	"priceToCashFlow": 0.7,
	"returnOnEquity": 27.21,
	"returnOnAssets": 0.38,
	"day21MovingAvg": 42.282253,
	"day50MovingAvg": 40.363613,
	"day200MovingAvg": 37.188126,
	"dividend3Years": "",
	"dividend5Years": "",
	"datatype": "equity",
	"issueType": "CS",
	"close": 44.53,
	"qmdescription": "Thrifts & Mortgage Financing",
	"__typename": "Company"
}