{
	"symbol": "HPR",
	"name": "Global X Active Preferred Share ETF",
	"price": 8.99,
	"priceChange": 0,
	"percentChange": 0,
	"exchangeName": "Toronto Stock Exchange",
	"exShortName": "TSX",
	"exchangeCode": "TSX",
	"marketPlace": null,
	"sector": "",
	"industry": "",
	"volume": 23006,
	"openPrice": 8.99,
	"dayHigh": 9,
	"dayLow": 8.98,
	"MarketCap": 1016254098,
	"MarketCapAllClasses": 0,
	"peRatio": 8.39,
	"prevClose": 8.99,
	"dividendFrequency": "Monthly",
	"dividendYield": 4.305,
	"dividendAmount": 0.0335,
	"dividendCurrency": "CAD",
	"beta": 0.817537,
	"eps": null,
	"exDividendDate": "2024-10-31 00:00:00.0",
	"longDescription": "In order to achieve its investment objective, by investing primarily in preferred shares including securities convertible into preferred shares of Canadian companies. HPR may also invest in preferred shares of companies located in the United States, debt securities, including limited resource capital notes, of Canadian and U.S. issuers, other income generating securities, as well as Canadian equity securities and Listed Funds, as they are defined in the ETFs prospectus. The investment objective of HPR is to provide dividend income while preserving capital.",
	"fulldescription": "In order to achieve its investment objective, by investing primarily in preferred shares including securities convertible into preferred shares of Canadian companies. HPR may also invest in preferred shares of companies located in the United States, debt securities, including limited resource capital notes, of Canadian and U.S. issuers, other income generating securities, as well as Canadian equity securities and Listed Funds, as they are defined in the ETFs prospectus. The investment objective of HPR is to provide dividend income while preserving capital.",
	"website": "",
	"email": "",
	"phoneNumber": "",
	"fullAddress": "CA",
	"employees": "",
	"shareOutStanding": 113042725,
	"totalDebtToEquity": "",
	"totalSharesOutStanding": 0,
	"sharesESCROW": null,
	"vwap": 8.98855895,
	"dividendPayDate": "2024-11-07",
	"weeks52high": 9.06,
	"weeks52low": 7.36,
	"alpha": 0.001466,
	"averageVolume10D": 28714,
	"averageVolume20D": 23015,
	"averageVolume30D": 28614,
	"averageVolume50D": 32950,
	"priceToBook": 0.39,
	"priceToCashFlow": "",
	"returnOnEquity": "",
	"returnOnAssets": "",
	"day21MovingAvg": 8.912171,
	"day50MovingAvg": 8.928984,
	"day200MovingAvg": 8.543243,
	"dividend3Years": "",
	"dividend5Years": "",
	"datatype": "etf",
	"issueType": "",
	"close": 8.99,
	"qmdescription": "",
	"__typename": "Company"
}