{
	"symbol": "MPCT.DB.A",
	"name": "Dream Impact Trust 5.75% Convertible Unsecured Subordinated Debentures",
	"price": 99.99,
	"priceChange": 0,
	"percentChange": 0,
	"exchangeName": "Toronto Stock Exchange",
	"exShortName": "TSX",
	"exchangeCode": "TSX",
	"marketPlace": null,
	"sector": "Real Estate",
	"industry": "REITs",
	"volume": 0,
	"openPrice": null,
	"dayHigh": null,
	"dayLow": null,
	"MarketCap": 39996000,
	"MarketCapAllClasses": 1840833299,
	"peRatio": "",
	"prevClose": 99.99,
	"dividendFrequency": null,
	"dividendYield": null,
	"dividendAmount": null,
	"dividendCurrency": null,
	"beta": -0.033056,
	"eps": null,
	"exDividendDate": "",
	"longDescription": "Dream Impact Trust is a Canada-based open-ended trust. It is focused on asset alternative investments consisting of real estate, real estate lending, real estate development and renewable power.",
	"fulldescription": "Dream Impact Trust is a Canada-based open-ended trust. It is focused on asset alternative investments consisting of real estate, real estate lending, real estate development and renewable power.",
	"website": "http://www.dream.ca",
	"email": "",
	"phoneNumber": "",
	"fullAddress": "30 Adelaide Street East,Suite 301, CA",
	"employees": "0",
	"shareOutStanding": 400000,
	"totalDebtToEquity": 0.69,
	"totalSharesOutStanding": 18410174,
	"sharesESCROW": null,
	"vwap": null,
	"dividendPayDate": null,
	"weeks52high": 99.99,
	"weeks52low": 83.51,
	"alpha": 0.003058,
	"averageVolume10D": 0,
	"averageVolume20D": 4400,
	"averageVolume30D": 2933,
	"averageVolume50D": 2140,
	"priceToBook": 0.12,
	"priceToCashFlow": -7.9,
	"returnOnEquity": -5.93,
	"returnOnAssets": -3.51,
	"day21MovingAvg": 99.27571,
	"day50MovingAvg": 97.5276,
	"day200MovingAvg": 95.1277,
	"dividend3Years": -100,
	"dividend5Years": -100,
	"datatype": "equity",
	"issueType": "DB",
	"close": 99.99,
	"qmdescription": "Diversified REITs",
	"__typename": "Company"
}