{
	"symbol": "PPL",
	"name": "Pembina Pipeline Corporation",
	"price": 50.73,
	"priceChange": 0.22,
	"percentChange": 0.435557,
	"exchangeName": "Toronto Stock Exchange",
	"exShortName": "TSX",
	"exchangeCode": "TSX",
	"marketPlace": null,
	"sector": "Energy",
	"industry": "Oil & Gas Storage/Transport",
	"volume": 454344,
	"openPrice": 50.56,
	"dayHigh": 50.84,
	"dayLow": 50.51,
	"MarketCap": 29469765191,
	"MarketCapAllClasses": 29469462840,
	"peRatio": 16.56,
	"prevClose": 50.51,
	"dividendFrequency": "Quarterly",
	"dividendYield": 5.598,
	"dividendAmount": 0.71,
	"dividendCurrency": "CAD",
	"beta": 0.857863,
	"eps": 3.07,
	"exDividendDate": "2025-06-16 00:00:00.0",
	"longDescription": "Pembina Pipeline is midstream company serving the Canadian and North American ( primarily Bakken) markets with an integrated product portfolio. The firms' assets include pipelines and gas gathering, as well as assets across fractionation, storage, and propane exports.",
	"fulldescription": "Pembina Pipeline is midstream company serving the Canadian and North American ( primarily Bakken) markets with an integrated product portfolio. The firms' assets include pipelines and gas gathering, as well as assets across fractionation, storage, and propane exports.",
	"website": "https://www.pembina.com",
	"email": "investor-relations@pembina.com",
	"phoneNumber": "+1 403 231-7500",
	"fullAddress": "585 - 8th Avenue S.W.,Suite 4000, Calgary, AB, CA",
	"employees": "2837",
	"shareOutStanding": 580913960,
	"totalDebtToEquity": 0.75,
	"totalSharesOutStanding": 580908000,
	"sharesESCROW": null,
	"vwap": 50.7037427,
	"dividendPayDate": "2025-06-30",
	"weeks52high": 60.72,
	"weeks52low": 48.35,
	"alpha": 0.005267,
	"averageVolume10D": 4722518,
	"averageVolume20D": 5049224,
	"averageVolume30D": 4363556,
	"averageVolume50D": 3865979,
	"priceToBook": 1.68,
	"priceToCashFlow": 8.8,
	"returnOnEquity": 12.16,
	"returnOnAssets": 5.91,
	"day21MovingAvg": 50.905777,
	"day50MovingAvg": 51.455402,
	"day200MovingAvg": 53.04117,
	"dividend3Years": 3.08,
	"dividend5Years": 2.33,
	"datatype": "equity",
	"issueType": "CS",
	"close": 50.73,
	"qmdescription": "Oil & Gas Storage/Transport",
	"__typename": "Company"
}