{
	"symbol": "PZW.U",
	"name": "Invesco FTSE RAFI Global Small-Mid ETF",
	"price": 25.4,
	"priceChange": -0.44,
	"percentChange": -1.702786,
	"exchangeName": "Toronto Stock Exchange",
	"exShortName": "TSX",
	"exchangeCode": "TSX",
	"marketPlace": null,
	"sector": "",
	"industry": "",
	"volume": 0,
	"openPrice": null,
	"dayHigh": null,
	"dayLow": null,
	"MarketCap": 1016000,
	"MarketCapAllClasses": 0,
	"peRatio": 0,
	"prevClose": 25.84,
	"dividendFrequency": "Quarterly",
	"dividendYield": 2.728,
	"dividendAmount": 0.10629,
	"dividendCurrency": "USD",
	"beta": 1.053714,
	"eps": null,
	"exDividendDate": "2024-09-27 00:00:00.0",
	"longDescription": "PZW seeks to generate capital growth over the longterm by investing directly or indirectly primarily in equities of small and mediumsized companies from developed markets globally. Invesco FTSE RAFI Global Small-Mid ETF (the ETF) seeks to replicate, before fees and expenses, the price and yield of the FTSE RAFI US 1500 Small-Mid Index and the FTSE RAFI Developed ex U.S. Mid Small 1500 Index, respectively (each, an underlying index).",
	"fulldescription": "PZW seeks to generate capital growth over the longterm by investing directly or indirectly primarily in equities of small and mediumsized companies from developed markets globally. Invesco FTSE RAFI Global Small-Mid ETF (the ETF) seeks to replicate, before fees and expenses, the price and yield of the FTSE RAFI US 1500 Small-Mid Index and the FTSE RAFI Developed ex U.S. Mid Small 1500 Index, respectively (each, an underlying index). This ETF gives investors exposures to small- and medium-sized companies from developed markets globally with the highest fundamental weightings using the Fundamental Index methodology developed by Research Affiliates, LLC.",
	"website": "www.invesco.ca",
	"email": "",
	"phoneNumber": "+1 8008746275",
	"fullAddress": "5140 Yonge Street, Suite 900, Toronto, ON, CA",
	"employees": "",
	"shareOutStanding": 40000,
	"totalDebtToEquity": "",
	"totalSharesOutStanding": 0,
	"sharesESCROW": null,
	"vwap": null,
	"dividendPayDate": "2024-10-07",
	"weeks52high": 26.35,
	"weeks52low": 21.402686,
	"alpha": -0.000302,
	"averageVolume10D": 0,
	"averageVolume20D": 135,
	"averageVolume30D": 163,
	"averageVolume50D": 200,
	"priceToBook": 0,
	"priceToCashFlow": 7.1,
	"returnOnEquity": 12.74,
	"returnOnAssets": 4.94,
	"day21MovingAvg": 25.675238,
	"day50MovingAvg": 25.763794,
	"day200MovingAvg": 24.57734,
	"dividend3Years": "",
	"dividend5Years": "",
	"datatype": "etf",
	"issueType": "ET",
	"close": 26.12,
	"qmdescription": "",
	"__typename": "Company"
}