{
	"symbol": "QLB",
	"name": "Mackenzie Canadian Government Long Bond Index ETF",
	"price": 101.7,
	"priceChange": -0.01,
	"percentChange": -0.009832,
	"exchangeName": "Toronto Stock Exchange",
	"exShortName": "TSX",
	"exchangeCode": "TSX",
	"marketPlace": null,
	"sector": "",
	"industry": "",
	"volume": 50,
	"openPrice": null,
	"dayHigh": null,
	"dayLow": null,
	"MarketCap": 67122000,
	"MarketCapAllClasses": 0,
	"peRatio": "",
	"prevClose": 101.71,
	"dividendFrequency": "Monthly",
	"dividendYield": 3.376,
	"dividendAmount": 0.31377,
	"dividendCurrency": "CAD",
	"beta": 0.934202,
	"eps": null,
	"exDividendDate": "2024-11-01 00:00:00.0",
	"longDescription": "The ETF seeks to replicate, to the extent reasonably possible and before fees and expenses, the performance of the Solactive Canadian Long Term Government Bond Index, or any successor thereto. It invests primarily in Canadian federal and provincial government long dated debt instruments. The Fund seeks to provide longterm capital appreciation.",
	"fulldescription": "The ETF seeks to replicate, to the extent reasonably possible and before fees and expenses, the performance of the Solactive Canadian Long Term Government Bond Index, or any successor thereto. It invests primarily in Canadian federal and provincial government long dated debt instruments. The Fund seeks to provide longterm capital appreciation.",
	"website": "",
	"email": "",
	"phoneNumber": "",
	"fullAddress": "CA",
	"employees": "",
	"shareOutStanding": 660000,
	"totalDebtToEquity": "",
	"totalSharesOutStanding": 0,
	"sharesESCROW": null,
	"vwap": null,
	"dividendPayDate": "2024-11-08",
	"weeks52high": 110.02,
	"weeks52low": 94.562481,
	"alpha": -0.009937,
	"averageVolume10D": 822,
	"averageVolume20D": 428,
	"averageVolume30D": 393,
	"averageVolume50D": 949,
	"priceToBook": null,
	"priceToCashFlow": "",
	"returnOnEquity": "",
	"returnOnAssets": "",
	"day21MovingAvg": 104.247986,
	"day50MovingAvg": 104.66579,
	"day200MovingAvg": 101.81313,
	"dividend3Years": "",
	"dividend5Years": "",
	"datatype": "etf",
	"issueType": "",
	"close": 102.59,
	"qmdescription": "",
	"__typename": "Company"
}