{
	"symbol": "SBI",
	"name": "Serabi Gold plc Ordinary Shares",
	"price": 1.59,
	"priceChange": 0.02,
	"percentChange": 1.273885,
	"exchangeName": "Toronto Stock Exchange",
	"exShortName": "TSX",
	"exchangeCode": "TSX",
	"marketPlace": null,
	"sector": "Materials",
	"industry": "Mining",
	"volume": 8125,
	"openPrice": 1.59,
	"dayHigh": 1.6,
	"dayLow": 1.58,
	"MarketCap": 120417937,
	"MarketCapAllClasses": 120417937,
	"peRatio": 41.3,
	"prevClose": 1.57,
	"dividendFrequency": null,
	"dividendYield": null,
	"dividendAmount": null,
	"dividendCurrency": null,
	"beta": 1.67365,
	"eps": 0.19,
	"exDividendDate": "",
	"longDescription": "Serabi Gold PLC is a gold exploration and production company. It is involved in the evaluation and development of gold deposits in Brazil. The company has two geographical segments namely Brazil and the UK. It generates maximum revenue from the Brazil region. The company projects include Palito, Sao Chico Gold Mines, Coringa, Jardim do Ouro and Tapajos Regional Exploration. It derives its majority revenue from the sale of gold.",
	"fulldescription": "Serabi Gold PLC is a gold exploration and production company. It is involved in the evaluation and development of gold deposits in Brazil. The company has two geographical segments namely Brazil and the UK. It generates maximum revenue from the Brazil region. The company projects include Palito, Sao Chico Gold Mines, Coringa, Jardim do Ouro and Tapajos Regional Exploration. It derives its majority revenue from the sale of gold.",
	"website": "https://www.serabigold.com",
	"email": "IR@Serabigold.com",
	"phoneNumber": "+44 2072466830",
	"fullAddress": "30-32 Ludgate Hill,2nd Floor, London, GB",
	"employees": "655",
	"shareOutStanding": 75734551,
	"totalDebtToEquity": 0,
	"totalSharesOutStanding": 75734551,
	"sharesESCROW": null,
	"vwap": 1.59,
	"dividendPayDate": null,
	"weeks52high": 1.9,
	"weeks52low": 0.55,
	"alpha": 0.008663,
	"averageVolume10D": 11892,
	"averageVolume20D": 16302,
	"averageVolume30D": 17422,
	"averageVolume50D": 22537,
	"priceToBook": 1.03,
	"priceToCashFlow": 5.2,
	"returnOnEquity": -1.16,
	"returnOnAssets": -0.96,
	"day21MovingAvg": 1.606667,
	"day50MovingAvg": 1.5764,
	"day200MovingAvg": 1.2551,
	"dividend3Years": "",
	"dividend5Years": "",
	"datatype": "equity",
	"issueType": "CS",
	"close": 1.59,
	"qmdescription": "Gold",
	"__typename": "Company"
}