{
	"symbol": "STCK",
	"name": "Stack Capital Group Inc.",
	"price": 13.15,
	"priceChange": -0.01,
	"percentChange": -0.075988,
	"exchangeName": "Toronto Stock Exchange",
	"exShortName": "TSX",
	"exchangeCode": "TSX",
	"marketPlace": null,
	"sector": "Finance",
	"industry": "Asset Management Services",
	"volume": 3555,
	"openPrice": 13.32,
	"dayHigh": 13.32,
	"dayLow": 13,
	"MarketCap": 140540941,
	"MarketCapAllClasses": 140812357,
	"peRatio": 11.34,
	"prevClose": 13.16,
	"dividendFrequency": null,
	"dividendYield": null,
	"dividendAmount": null,
	"dividendCurrency": null,
	"beta": 0.580564,
	"eps": 1.18,
	"exDividendDate": "",
	"longDescription": "Stack Capital Group Inc is a newly formed investment holding company. It is focused on investing in growth to late-stage private issuers with operating businesses, with long-term growth potential, located in, or with customers, suppliers or business primarily conducted in or dependent on, Canada or the United States. Its business objective is to maximize its long-term capital appreciation by seeking to achieve superior risk-adjusted investment performance.",
	"fulldescription": "Stack Capital Group Inc is a newly formed investment holding company. It is focused on investing in growth to late-stage private issuers with operating businesses, with long-term growth potential, located in, or with customers, suppliers or business primarily conducted in or dependent on, Canada or the United States. Its business objective is to maximize its long-term capital appreciation by seeking to achieve superior risk-adjusted investment performance.",
	"website": "https://www.stackcapitalgroup.com",
	"email": "",
	"phoneNumber": "+1 647 280-3307",
	"fullAddress": "155 Wellington Street West,Suite 3140, Toronto, ON, CA",
	"employees": "0",
	"shareOutStanding": 10687524,
	"totalDebtToEquity": 0,
	"totalSharesOutStanding": 10708164,
	"sharesESCROW": null,
	"vwap": 13.1385714,
	"dividendPayDate": null,
	"weeks52high": 13.32,
	"weeks52low": 9,
	"alpha": 0.001628,
	"averageVolume10D": 14060,
	"averageVolume20D": 20488,
	"averageVolume30D": 18779,
	"averageVolume50D": 18881,
	"priceToBook": 1.09,
	"priceToCashFlow": -9.3,
	"returnOnEquity": 10.47,
	"returnOnAssets": 10.42,
	"day21MovingAvg": 12.698095,
	"day50MovingAvg": 11.9032,
	"day200MovingAvg": 11.10495,
	"dividend3Years": "",
	"dividend5Years": "",
	"datatype": "equity",
	"issueType": "CS",
	"close": 13.15,
	"qmdescription": "Asset Management Services",
	"__typename": "Company"
}