{
	"symbol": "VDU",
	"name": "Vanguard FTSE Developed All Cap Ex U.S. Index ETF",
	"price": 48.77,
	"priceChange": -0.1,
	"percentChange": -0.204625,
	"exchangeName": "Toronto Stock Exchange",
	"exShortName": "TSX",
	"exchangeCode": "TSX",
	"marketPlace": null,
	"sector": "",
	"industry": "",
	"volume": 4671,
	"openPrice": 48.87,
	"dayHigh": 48.87,
	"dayLow": 48.67,
	"MarketCap": 559967386,
	"MarketCapAllClasses": 0,
	"peRatio": 14.83,
	"prevClose": 48.87,
	"dividendFrequency": "Quarterly",
	"dividendYield": 2.168,
	"dividendAmount": 0.311859,
	"dividendCurrency": "CAD",
	"beta": 0.819232,
	"eps": null,
	"exDividendDate": "2025-06-20 00:00:00.0",
	"longDescription": "The investment objective of Vanguard FTSE Developed All Cap ex U.S. Index ETF (the ETF) is to track, to the extent reasonably possible and before fees and expenses, the performance of the FTSE Developed All Cap ex US Index (the Index). The Index is a market capitalization-weighted index representing the performance of large-, mid- and small-capitalization stocks in developed markets, excluding the United States. The fund seeks to track, to the extent reasonably possible and before fees and expenses, the performance of a broad global equityindex that focuses on providing coverage of developed markets, excluding the U.S. Currently, this Vanguard ETF seeks to trackthe FTSE Developed All Cap ex US Index (or any successor thereto).",
	"fulldescription": "The investment objective of Vanguard FTSE Developed All Cap ex U.S. Index ETF (the ETF) is to track, to the extent reasonably possible and before fees and expenses, the performance of the FTSE Developed All Cap ex US Index (the Index). The Index is a market capitalization-weighted index representing the performance of large-, mid- and small-capitalization stocks in developed markets, excluding the United States. The fund seeks to track, to the extent reasonably possible and before fees and expenses, the performance of a broad global equityindex that focuses on providing coverage of developed markets, excluding the U.S. Currently, this Vanguard ETF seeks to trackthe FTSE Developed All Cap ex US Index (or any successor thereto). It invests directly or indirectly primarily in large-, mid-, andsmall-capitalization stocks of companies located in developed markets, excluding the U.S.",
	"website": "www.vanguardcanada.ca",
	"email": "",
	"phoneNumber": "888-293-6729",
	"fullAddress": "22 Adelaide St West, Suite 2500, Toronto, ON, CA",
	"employees": "",
	"shareOutStanding": 11481800,
	"totalDebtToEquity": "",
	"totalSharesOutStanding": 0,
	"sharesESCROW": null,
	"vwap": 48.785,
	"dividendPayDate": "2025-06-27",
	"weeks52high": 49.09,
	"weeks52low": 39.9,
	"alpha": 0.0011,
	"averageVolume10D": 36853,
	"averageVolume20D": 29277,
	"averageVolume30D": 25576,
	"averageVolume50D": 25771,
	"priceToBook": 0.65,
	"priceToCashFlow": 8.7,
	"returnOnEquity": 16.11,
	"returnOnAssets": 6.05,
	"day21MovingAvg": 48.22327,
	"day50MovingAvg": 47.486126,
	"day200MovingAvg": 44.94277,
	"dividend3Years": "",
	"dividend5Years": "",
	"datatype": "etf",
	"issueType": "ET",
	"close": 48.77,
	"qmdescription": "",
	"__typename": "Company"
}