{
	"symbol": "ZCB",
	"name": "BMO Corporate Bond Index ETF",
	"price": 47.27,
	"priceChange": 0.05,
	"percentChange": 0.105887,
	"exchangeName": "Toronto Stock Exchange",
	"exShortName": "TSX",
	"exchangeCode": "TSX",
	"marketPlace": null,
	"sector": "",
	"industry": "",
	"volume": 957,
	"openPrice": 47.35,
	"dayHigh": 47.35,
	"dayLow": 47.22,
	"MarketCap": 161852480,
	"MarketCapAllClasses": 0,
	"peRatio": "",
	"prevClose": 47.22,
	"dividendFrequency": "Quarterly",
	"dividendYield": 3.913,
	"dividendAmount": 0.47,
	"dividendCurrency": "CAD",
	"beta": 0.242603,
	"eps": null,
	"exDividendDate": "2025-06-27 00:00:00.0",
	"longDescription": "The ETF seeks to replicate, to the extent possible, the performance of a corporate bond index, net of expenses. To achieve investment objective The investment strategy of the ETF is to invest in and hold the constituent securities of the Index in the same proportion as they are reflected in the Index. The Manager may also use a sampling methodology in selecting investments for the ETF. As an alternative to or in conjunction with investing in and holding the constituent securities, the ETF may invest in or use certain Other Securities (as defined in the prospectus) to obtain exposure to the performance of the Index.",
	"fulldescription": "The ETF seeks to replicate, to the extent possible, the performance of a corporate bond index, net of expenses. To achieve investment objective The investment strategy of the ETF is to invest in and hold the constituent securities of the Index in the same proportion as they are reflected in the Index. The Manager may also use a sampling methodology in selecting investments for the ETF. As an alternative to or in conjunction with investing in and holding the constituent securities, the ETF may invest in or use certain Other Securities (as defined in the prospectus) to obtain exposure to the performance of the Index.",
	"website": "www.bmo.com/gam/ca",
	"email": "alternativeproducts@bmo.com",
	"phoneNumber": "+1 8003611392",
	"fullAddress": "43rd Floor, 100 King Street West, Toronto, ON, CA",
	"employees": "",
	"shareOutStanding": 3424000,
	"totalDebtToEquity": "",
	"totalSharesOutStanding": 0,
	"sharesESCROW": null,
	"vwap": 47.2744444,
	"dividendPayDate": "2025-07-03",
	"weeks52high": 48.25,
	"weeks52low": 44.076661,
	"alpha": -0.00114,
	"averageVolume10D": 2347,
	"averageVolume20D": 2255,
	"averageVolume30D": 2323,
	"averageVolume50D": 2111,
	"priceToBook": null,
	"priceToCashFlow": "",
	"returnOnEquity": "",
	"returnOnAssets": "",
	"day21MovingAvg": 47.128735,
	"day50MovingAvg": 47.027206,
	"day200MovingAvg": 46.487816,
	"dividend3Years": "",
	"dividend5Years": "",
	"datatype": "etf",
	"issueType": "ET",
	"close": 47.28,
	"qmdescription": "",
	"__typename": "Company"
}